topsis/__init__.py
topsis/__main__.py
topsis/main.py
Topsis_Yashika_101903787-1.0.0.dist-info/METADATA
Topsis_Yashika_101903787-1.0.0.dist-info/WHEEL
Topsis_Yashika_101903787-1.0.0.dist-info/top_level.txt
Topsis_Yashika_101903787-1.0.0.dist-info/RECORD
